matcha_dl/__init__.py
matcha_dl/core/__init__.py
matcha_dl/core/actions/__init__.py
matcha_dl/core/actions/alignment.py
matcha_dl/core/contracts/__init__.py
matcha_dl/core/contracts/loss.py
matcha_dl/core/contracts/matcha.py
matcha_dl/core/contracts/model.py
matcha_dl/core/contracts/negative_sampler.py
matcha_dl/core/contracts/processor.py
matcha_dl/core/contracts/stopper.py
matcha_dl/core/contracts/trainer.py
matcha_dl/core/entities/__init__.py
matcha_dl/core/entities/configs/__init__.py
matcha_dl/core/entities/configs/config.py
matcha_dl/core/entities/dataset.py
matcha_dl/core/values.py
matcha_dl/default_config.yaml
matcha_dl/delivery/__init__.py
matcha_dl/delivery/api.py
matcha_dl/delivery/cli.py
matcha_dl/impl/__init__.py
matcha_dl/impl/dp/__init__.py
matcha_dl/impl/dp/utils.py
matcha_dl/impl/losses/__init__.py
matcha_dl/impl/losses/bceloss.py
matcha_dl/impl/matcha/__init__.py
matcha_dl/impl/matcha/matcha.py
matcha_dl/impl/models/__init__.py
matcha_dl/impl/models/model.py
matcha_dl/impl/negative_sampler.py
matcha_dl/impl/processor.py
matcha_dl/impl/stoppers/__init__.py
matcha_dl/impl/stoppers/earlystoping.py
matcha_dl/impl/trainer.py
matcha_dl-0.1.1.dist-info/LICENSE
matcha_dl-0.1.1.dist-info/METADATA
matcha_dl-0.1.1.dist-info/WHEEL
matcha_dl-0.1.1.dist-info/entry_points.txt
matcha_dl-0.1.1.dist-info/RECORD
