Metadata-Version: 2.1
Name: matcha-dl
Version: 0.1.1
Summary: Matcha-DL is a tool for supervised ontology alignment. It takes as input two ontologies and a set of mappings between them, and learns a model that can predict mappings between the two ontologies.
Home-page: https://github.com/liseda-lab/Matcha-DL
Author: Pedro Cotovio
Author-email: pgcotovio@gmail.com
Requires-Python: >=3.10,<4.0
Classifier: Programming Language :: Python :: 3
Classifier: Programming Language :: Python :: 3.10
Classifier: Programming Language :: Python :: 3.11
Classifier: Programming Language :: Python :: 3.12
Requires-Dist: deeponto (>=0.9.1,<0.10.0)
Requires-Dist: dill (>=0.3.8,<0.4.0)
Requires-Dist: lxml (>=5.2.1,<6.0.0)
Requires-Dist: pandas (>=2.2.2,<3.0.0)
Requires-Dist: pyyaml (>=6.0.1,<7.0.0)
Requires-Dist: sentence-transformers (>=2.7.0,<3.0.0)
Requires-Dist: tensorboard (>=2.16.2,<3.0.0)
Requires-Dist: torch (>=2.3.0,<3.0.0)
Project-URL: Repository, https://github.com/liseda-lab/Matcha-DL
